PyDrive-1.2.1.dist-info/DESCRIPTION.rst
PyDrive-1.2.1.dist-info/METADATA
PyDrive-1.2.1.dist-info/RECORD
PyDrive-1.2.1.dist-info/WHEEL
PyDrive-1.2.1.dist-info/metadata.json
PyDrive-1.2.1.dist-info/top_level.txt
pydrive/__init__.py
pydrive/apiattr.py
pydrive/auth.py
pydrive/drive.py
pydrive/files.py
pydrive/settings.py
pydrive/test/__init__.py
pydrive/test/test_apiattr.py
pydrive/test/test_drive.py
pydrive/test/test_file.py
pydrive/test/test_filelist.py
pydrive/test/test_oauth.py
pydrive/test/test_util.py
