Metadata-Version: 1.0
Name: PyDrive
Version: 1.2.1
Summary: Google Drive API made easy.
Home-page: https://github.com/googledrive/PyDrive
Author: Robin Nabel
Author-email: rnabel@ucdavis.edu
License: LICENSE
Platform: UNKNOWN
